{
  "$schema": "https://raw.githubusercontent.com/jopemachine/arvis-extension-validator/master/workflow-schema.json",
  "category": "Productivity",
  "creator": "Sindre Sorhus",
  "description": "Lock your Mac",
  "name": "Lock",
  "readme": "",
  "webAddress": "",
  "version": "0.0.4",
  "defaultIcon": "icon.png",
  "enabled": true,
  "commands": [
    {
      "type": "keyword",
      "command": "lock",
      "title": "Lock",
      "subtitle": "",
      "argType": "no",
      "actions": [
        {
          "modifiers": "normal",
          "type": "script",
          "script": "./lock"
        }
      ]
    }
  ]
}
